{
  "db_name": "PostgreSQL",
  "query": "select id, user_id, payload as \"payload: Json<NotificationPayload>\", created_at, read from notifications where user_id = $1 and id = $2",
  "describe": {
    "columns": [
      {
        "ordinal": 0,
        "name": "id",
        "type_info": "Int8"
      },
      {
        "ordinal": 1,
        "name": "user_id",
        "type_info": "Int8"
      },
      {
        "ordinal": 2,
        "name": "payload: Json<NotificationPayload>",
        "type_info": "Jsonb"
      },
      {
        "ordinal": 3,
        "name": "created_at",
        "type_info": "Timestamptz"
      },
      {
        "ordinal": 4,
        "name": "read",
        "type_info": "Bool"
      }
    ],
    "parameters": {
      "Left": [
        "Int8",
        "Int8"
      ]
    },
    "nullable": [
      false,
      false,
      false,
      false,
      false
    ]
  },
  "hash": "035fef58306cc0e58b1d465365efde0b550ef3706988ca53f5610763b2a3a7c5"
}
